{
    "sv": {
        "welcome": "välkommen",
        "username": "Användare",
        "password": "Lösenord",
        "guest_login" : "Logga in som gäst",
        "login": "Logga in",
        "statistics": "Statistik",
        "order": "Beställ",
        "undo": "Ångra",
        "redo": "Gör om",
        "total sum": "Total summa:",
        "credit": "Kredit: £",
        "invEdit": "Ändra",
        "purchases": "Historik",
        "inventory": "Lager",
        "users": "Användare",
        "newName": "Nytt användarnamn",
        "newPW": "Nytt lösenord",
        "newEmail": "Ny mail",
        "newPhoneNr": "Nytt telefonnummer",
        "username:": "Användarnamn",
        "firstname": "Förnamn",
        "lastname": "Efternamn",
        "credits": "Kredit"
    },
    "en": {
        "welcome": "Welcome",
        "username": "Username",
        "password": "Password",
        "guest_login": "Login as guest",
        "login": "Login",
        "statistics": "Statistics",
        "order": "Order",
        "undo": "Undo",
        "redo": "Redo",
        "total sum": "Total sum:",
        "credit": "Credit: £",
        "invEdit": "Edit",
        "purchases": "Purchases",
        "inventory": "Inventory",
        "users": "Users",
        "newName": "New username",
        "newPW": "New password",
        "newEmail": "New email",
        "newPhoneNr": "New phone number",
        "username:": "Username",
        "firstname": "First name",
        "lastname": "Last name",
        "credits": "Credits"
    }
}
